twitter_graphql/__init__.py
twitter_graphql/constants.py
twitter_graphql/gql.py
twitter_graphql-0.0.0.dist-info/LICENSE
twitter_graphql-0.0.0.dist-info/METADATA
twitter_graphql-0.0.0.dist-info/WHEEL
twitter_graphql-0.0.0.dist-info/top_level.txt
twitter_graphql-0.0.0.dist-info/RECORD
