Metadata-Version: 2.1
Name: twitter-graphql
Version: 0.0.0
Summary: Unofficial Twitter GraphQL API
Home-page: https://github.com/trevorhobenshield/twitter-graphql
Author: Trevor Hobenshield
Author-email: trevorhobenshield@gmail.com
Keywords: twitter api graphql client
Requires-Python: >=3.11.0
License-File: LICENSE
Requires-Dist: httpx
Requires-Dist: nest-asyncio
Requires-Dist: orjson
Requires-Dist: tqdm
Requires-Dist: uvloop ; platform_system != "Windows"
